pinject_design/__init__.py
pinject_design/di/__init__.py
pinject_design/di/app_designed.py
pinject_design/di/app_injected.py
pinject_design/di/applicative.py
pinject_design/di/ast.py
pinject_design/di/bindings.py
pinject_design/di/design.py
pinject_design/di/designed.py
pinject_design/di/dynamic_proxy.py
pinject_design/di/graph.py
pinject_design/di/implicit_globals.py
pinject_design/di/injected.py
pinject_design/di/injected_analysis.py
pinject_design/di/modular_injected.py
pinject_design/di/permissioned/__init__.py
pinject_design/di/permissioned/blueprint.py
pinject_design/di/playground.py
pinject_design/di/provider.py
pinject_design/di/proxiable.py
pinject_design/di/session.py
pinject_design/di/sessioned.py
pinject_design/di/static_proxy.py
pinject_design/di/test_ast.py
pinject_design/di/test_dynamic_proxy.py
pinject_design/di/test_graph.py
pinject_design/di/test_injected.py
pinject_design/di/test_proxiable.py
pinject_design/di/util.py
pinject_design/exceptions.py
pinject_design/global_configs
pinject_design/global_configs.py
pinject_design/graph_inspection.py
pinject_design/helper_structure.py
pinject_design/helpers.py
pinject_design/module_inspector.py
pinject_design/nx_graph_util.py
pinject_design/pinject_design.iml
pinject_design/run_config_utils.py
pinject_design/run_config_utils_v2.py
pinject_design/test_package/__init__.py
pinject_design/test_package/child/__init__.py
pinject_design/test_package/child/module1.py
pinject_design/visualize_di.py
pinject_design/viz/__init__.py
pinject_design/viz/graph.py
pinject_design-0.1.107.dist-info/LICENSE
pinject_design-0.1.107.dist-info/METADATA
pinject_design-0.1.107.dist-info/WHEEL
pinject_design-0.1.107.dist-info/entry_points.txt
pinject_design-0.1.107.dist-info/RECORD
