Metadata-Version: 2.1
Name: pinject-design
Version: 0.1.107
Summary: immutable wrapper for pinject
License: MIT
Author: proboscis
Author-email: nameissoap@gmail.com
Requires-Python: >=3.10,<4.0
Classifier: License :: OSI Approved :: MIT License
Classifier: Programming Language :: Python :: 3
Classifier: Programming Language :: Python :: 3.10
Classifier: Programming Language :: Python :: 3.11
Requires-Dist: cloudpickle (>=2.2.1,<3.0.0)
Requires-Dist: cytoolz (>=0.12.2,<0.13.0)
Requires-Dist: expression (>=4.2.4,<5.0.0)
Requires-Dist: fire (>=0.5.0,<0.6.0)
Requires-Dist: frozendict (>=2.3.8,<3.0.0)
Requires-Dist: loguru (>=0.7.0,<0.8.0)
Requires-Dist: makefun (>=1.15.1,<2.0.0)
Requires-Dist: networkx (>=3.1,<4.0)
Requires-Dist: pydantic (>=2.1.1,<3.0.0)
Requires-Dist: pyvis (>=0.3.2,<0.4.0)
Requires-Dist: pyyaml (>=6.0.1,<7.0.0)
Requires-Dist: returns (>=0.21.0,<0.22.0)
Requires-Dist: tabulate (>=0.9.0,<0.10.0)
